taskstodo/calcurse.py
taskstodo/tasklists.py
taskstodo/tasks.py
taskstodo/taskstodo.py
taskstodo-0.0.5.dist-info/LICENSE
taskstodo-0.0.5.dist-info/METADATA
taskstodo-0.0.5.dist-info/WHEEL
taskstodo-0.0.5.dist-info/entry_points.txt
taskstodo-0.0.5.dist-info/top_level.txt
taskstodo-0.0.5.dist-info/RECORD
