Metadata-Version: 2.1
Name: taskstodo
Version: 0.0.5
Summary: Manage Google Tasks from the command-line and sync tasks with other apps.
Author: Stephan T
Project-URL: Homepage, https://github.com/stephan49/taskstodo
Project-URL: Bug Tracker, https://github.com/stephan49/taskstodo/issues
Classifier: Programming Language :: Python :: 3
Classifier: Operating System :: POSIX :: Linux
Classifier: License :: OSI Approved :: MIT License
Requires-Python: >=3.7
License-File: LICENSE
Requires-Dist: google-api-python-client
Requires-Dist: google-auth-httplib2
Requires-Dist: google-auth-oauthlib
